asencis/__init__.py
asencis/client.py
asencis/exceptions.py
asencis/mixins.py
asencis/response.py
asencis/utils.py
asencis/version.py
asencis/resources/__init__.py
asencis/resources/dataset.py
asencis/resources/domain.py
asencis/resources/prefix.py
asencis/resources/quantity.py
asencis-0.1.2.dist-info/LICENSE
asencis-0.1.2.dist-info/METADATA
asencis-0.1.2.dist-info/WHEEL
asencis-0.1.2.dist-info/top_level.txt
asencis-0.1.2.dist-info/RECORD
