Metadata-Version: 2.1
Name: asencis
Version: 0.1.2
Summary: asencis Python driver
Home-page: https://github.com/asencis/asencis-python
Author: asencis Ltd
Author-email: priority@asencis.com
License: MPL 2.0
Project-URL: Bug Tracker, https://github.com/asencis/asencis-python/issues
Project-URL: Documentation, https://asencis.com/documentation
Project-URL: Source Code, https://github.com/asencis/asencis-python
Keywords: asencis
Platform: UNKNOWN
Classifier: Development Status :: 5 - Production/Stable
Classifier: Intended Audience :: Developers
Classifier: License :: OSI Approved :: Mozilla Public License 2.0 (MPL 2.0)
Classifier: Programming Language :: Python :: 3
Classifier: Programming Language :: Python :: 3.3
Classifier: Programming Language :: Python :: 3.4
Classifier: Programming Language :: Python :: 3.5
Classifier: Programming Language :: Python :: 3.6
Classifier: Programming Language :: Python :: 3.7
Classifier: Programming Language :: Python :: Implementation :: PyPy
Classifier: Topic :: Software Development :: Libraries :: Python Modules
Classifier: Operating System :: MacOS :: MacOS X
Classifier: Operating System :: Microsoft :: Windows
Classifier: Operating System :: Unix
Requires-Dist: requests
Provides-Extra: doc
Requires-Dist: sphinx ; extra == 'doc'
Requires-Dist: sphinx-rtd-theme ; extra == 'doc'
Provides-Extra: lint
Requires-Dist: pylint ; extra == 'lint'
Provides-Extra: test
Requires-Dist: nose2 ; extra == 'test'
Requires-Dist: nose2[coverage_plugin] ; extra == 'test'
